killbills_sdk/__init__.py
killbills_sdk/cryptoService.py
killbills_sdk/example.py
killbills_sdk/sendDataWithHmac.py
killbills_sdk/validatorService.py
killbills_sdk-0.0.9.dist-info/METADATA
killbills_sdk-0.0.9.dist-info/WHEEL
killbills_sdk-0.0.9.dist-info/licenses/LICENSE
killbills_sdk-0.0.9.dist-info/RECORD
